valhalla/application.py
valhalla/converter.py
valhalla/decorators.py
valhalla/jwt.py
valhalla/models.py
valhalla/utils.py
valhalla/views/__init__.py
valhalla/views/auth.py
valhalla/views/texture.py
mc4ep_valhalla-0.3.2.dist-info/LICENSE
mc4ep_valhalla-0.3.2.dist-info/METADATA
mc4ep_valhalla-0.3.2.dist-info/WHEEL
mc4ep_valhalla-0.3.2.dist-info/top_level.txt
mc4ep_valhalla-0.3.2.dist-info/RECORD
